llama_optimus/__init__.py
llama_optimus/cli.py
llama_optimus/core.py
llama_optimus/override_patterns.py
llama_optimus/search_space.py
llama_optimus-0.1.9.dist-info/licenses/LICENSE
llama_optimus-0.1.9.dist-info/METADATA
llama_optimus-0.1.9.dist-info/WHEEL
llama_optimus-0.1.9.dist-info/entry_points.txt
llama_optimus-0.1.9.dist-info/top_level.txt
llama_optimus-0.1.9.dist-info/RECORD
