Metadata-Version: 2.4
Name: llama-optimus
Version: 0.1.9
Summary: llama-optimus is a lightweight Python tool to automatically optimize llama.cpp performance flags for maximum tg & pp token/s throughput. Powered by Bayesian optimization with Optuna
Author-email: Bruno Arsioli <YOUR_EMAIL@yourdomain.com>
License: MIT
Project-URL: Homepage, https://github.com/BrunoArsioli/llama-optimus
Project-URL: Repository, https://github.com/BrunoArsioli/llama-optimus
Project-URL: Bug Tracker, https://github.com/BrunoArsioli/llama-optimus/issues
Keywords: llama.cpp,optimization,AI,Optuna,performance
Classifier: Programming Language :: Python :: 3
Classifier: License :: OSI Approved :: MIT License
Classifier: Operating System :: OS Independent
Requires-Python: >=3.8
License-File: LICENSE
Requires-Dist: optuna>=3.0
Requires-Dist: pandas
Dynamic: license-file
